minha_biblioteca_string_utils/__init__.py
minha_biblioteca_string_utils/string_utils.py
minha_biblioteca_string_utils-0.1.0.dist-info/METADATA
minha_biblioteca_string_utils-0.1.0.dist-info/WHEEL
minha_biblioteca_string_utils-0.1.0.dist-info/top_level.txt
minha_biblioteca_string_utils-0.1.0.dist-info/RECORD
